AUTHORS
LICENSE
MANIFEST.in
README.md
setup.py
django_whistle.egg-info/PKG-INFO
django_whistle.egg-info/SOURCES.txt
django_whistle.egg-info/dependency_links.txt
django_whistle.egg-info/requires.txt
django_whistle.egg-info/top_level.txt
whistle/__init__.py
whistle/admin.py
whistle/api.py
whistle/forms.py
whistle/helpers.py
whistle/jobs.py
whistle/managers.py
whistle/middleware.py
whistle/mixins.py
whistle/models.py
whistle/settings.py
whistle/urls.py
whistle/views.py
whistle/locale/sk/LC_MESSAGES/django.mo
whistle/locale/sk/LC_MESSAGES/django.po
whistle/management/__init__.py
whistle/management/commands/__init__.py
whistle/management/commands/copy_channel_settings.py
whistle/management/commands/delete_old_notifications.py
whistle/migrations/0001_initial.py
whistle/migrations/0002_notification_details.py
whistle/migrations/0003_rename_web_settings.py
whistle/migrations/0004_rename_mail_to_email.py
whistle/migrations/0005_events_settings.py
whistle/migrations/0006_auto_20221116_1525.py
whistle/migrations/__init__.py
whistle/templates/whistle/notification_list.html
whistle/templates/whistle/settings.html
whistle/templates/whistle/mails/new_notification.txt