Metadata-Version: 2.1
Name: django-whistle
Version: 7.0.0
Summary: Advanced notifications for Django
Home-page: https://github.com/PragmaticMates/django-whistle
Author: Pragmatic Mates
Author-email: info@pragmaticmates.com
Maintainer: Pragmatic Mates
Maintainer-email: info@pragmaticmates.com
License: BSD License
Keywords: django notifications events push email iOS Android APN FireBase GCM
Platform: UNKNOWN
Classifier: Programming Language :: Python
Classifier: Operating System :: OS Independent
Classifier: Environment :: Web Environment
Classifier: Intended Audience :: Developers
Classifier: Framework :: Django
Classifier: License :: OSI Approved :: BSD License
Classifier: Development Status :: 5 - Production/Stable
License-File: LICENSE
License-File: AUTHORS
